asalytic/__init__.py
asalytic/db/__init__.py
asalytic/db/utils.py
asalytic/indexers/__init__.py
asalytic/indexers/indexer.py
asalytic/models/ASA.py
asalytic/models/ASACollection.py
asalytic/models/ASAListing.py
asalytic/models/ASAOwner.py
asalytic/models/ASAPriceEstimate.py
asalytic/models/ASARarity.py
asalytic/models/ASASale.py
asalytic/models/Listing.py
asalytic/models/Teal.py
asalytic/models/WalletConfiguration.py
asalytic/models/__init__.py
asalytic/models/algorand/Application.py
asalytic/models/algorand/ApplicationParams.py
asalytic/models/algorand/ApplicationTransaction.py
asalytic/models/algorand/AssetConfigTransaction.py
asalytic/models/algorand/AssetParams.py
asalytic/models/algorand/AssetTransferTransaction.py
asalytic/models/algorand/AtomicTransfer.py
asalytic/models/algorand/PaymentTransaction.py
asalytic/models/algorand/StateSchema.py
asalytic/models/algorand/TealKeyValue.py
asalytic/models/algorand/Transaction.py
asalytic/models/algorand/__init__.py
asalytic/models/applications/AsalyticApplicationListing.py
asalytic/models/applications/EXAApplicationListing.py
asalytic/models/applications/ShuflApplicationListing.py
asalytic/models/applications/__init__.py
asalytic/models/atomic_transfer/__init__.py
asalytic/models/atomic_transfer/delistings/AtomicTransferDelisting.py
asalytic/models/atomic_transfer/delistings/ShuflDelisting.py
asalytic/models/atomic_transfer/delistings/__init__.py
asalytic/models/atomic_transfer/delistings/smart_signatures/ALGOxNFTDelisting.py
asalytic/models/atomic_transfer/delistings/smart_signatures/AsalyticDelisting.py
asalytic/models/atomic_transfer/delistings/smart_signatures/SignatureDelisting.py
asalytic/models/atomic_transfer/delistings/smart_signatures/__init__.py
asalytic/models/atomic_transfer/listings/__init__.py
asalytic/models/atomic_transfer/listings/application/ATAppListing.py
asalytic/models/atomic_transfer/listings/application/AsalyticListing.py
asalytic/models/atomic_transfer/listings/application/EXAListings.py
asalytic-1.0.0.dist-info/licenses/LICENSE
asalytic-1.0.0.dist-info/METADATA
asalytic-1.0.0.dist-info/WHEEL
asalytic-1.0.0.dist-info/top_level.txt
asalytic-1.0.0.dist-info/RECORD
