Metadata-Version: 2.4
Name: asalytic
Version: 1.0.0
Summary: A Python library for tracking NFT sales and listings on the Algorand blockchain
License: MIT
Project-URL: Homepage, https://github.com/Vilijan/asalytic
Project-URL: Repository, https://github.com/Vilijan/asalytic
Project-URL: Issues, https://github.com/Vilijan/asalytic/issues
Keywords: algorand,nft,blockchain,sales,listings,asa,arc3,arc19,arc69
Classifier: Development Status :: 5 - Production/Stable
Classifier: Intended Audience :: Developers
Classifier: License :: OSI Approved :: MIT License
Classifier: Operating System :: OS Independent
Classifier: Programming Language :: Python :: 3
Classifier: Programming Language :: Python :: 3.8
Classifier: Programming Language :: Python :: 3.9
Classifier: Programming Language :: Python :: 3.10
Classifier: Programming Language :: Python :: 3.11
Classifier: Programming Language :: Python :: 3.12
Classifier: Topic :: Software Development :: Libraries :: Python Modules
Requires-Python: >=3.8
License-File: LICENSE
Requires-Dist: pydantic<2.0.0,>=1.8.0
Requires-Dist: pymongo>=3.12.0
Requires-Dist: py-algorand-sdk>=2.0.0
Requires-Dist: requests>=2.26.0
Requires-Dist: py-multihash>=1.1.0
Requires-Dist: py-cid>=0.3.0
Dynamic: license-file
